shameni/__init__.py
shameni/shameni.py
shameni/version.py
shameni-1.1.0.dist-info/LICENSE
shameni-1.1.0.dist-info/METADATA
shameni-1.1.0.dist-info/WHEEL
shameni-1.1.0.dist-info/top_level.txt
shameni-1.1.0.dist-info/RECORD
