Metadata-Version: 2.1
Name: shameni
Version: 1.1.0
Summary: The official Python wrapper for Presage, a straightforward cryptocurrency prediction service.
Home-page: https://github.com/rmaniego/shameni
Author: Rodney Maniego Jr.
Author-email: rod.maniego23@gmail.com
License: MIT
Download-URL: https://github.com/rmaniego/shameni/archive/v1.0.tar.gz
Keywords: presage,cryptocurrency,prediction,python,wrapper
Platform: UNKNOWN
Classifier: Development Status :: 5 - Production/Stable
Classifier: Intended Audience :: Developers
Classifier: Topic :: Software Development :: Build Tools
Classifier: License :: OSI Approved :: MIT License
Classifier: Programming Language :: Python :: 3
Requires-Python: >=3.6
License-File: LICENSE
Requires-Dist: requests
Requires-Dist: arkivist
Requires-Dist: sometime
